neon_diagrams/__init__.py
neon_diagrams/web.py
neon_diagrams-0.1.0.dist-info/WHEEL
neon_diagrams-0.1.0.dist-info/METADATA
neon_diagrams-0.1.0.dist-info/RECORD
